{
  "config": {
    "n_strains": 200,
    "n_features": 50,
    "n_true_associations": 20,
    "association_strength": 0.6,
    "background_prevalence": 0.3,
    "noise_level": 0.05,
    "random_state": 42
  },
  "n_true_associations": 20,
  "expected_network_edges": 20,
  "feature_columns": [
    "Feature_001",
    "Feature_002",
    "Feature_003",
    "Feature_004",
    "Feature_005",
    "Feature_006",
    "Feature_007",
    "Feature_008",
    "Feature_009",
    "Feature_010",
    "Feature_011",
    "Feature_012",
    "Feature_013",
    "Feature_014",
    "Feature_015",
    "Feature_016",
    "Feature_017",
    "Feature_018",
    "Feature_019",
    "Feature_020",
    "Feature_021",
    "Feature_022",
    "Feature_023",
    "Feature_024",
    "Feature_025",
    "Feature_026",
    "Feature_027",
    "Feature_028",
    "Feature_029",
    "Feature_030",
    "Feature_031",
    "Feature_032",
    "Feature_033",
    "Feature_034",
    "Feature_035",
    "Feature_036",
    "Feature_037",
    "Feature_038",
    "Feature_039",
    "Feature_040",
    "Feature_041",
    "Feature_042",
    "Feature_043",
    "Feature_044",
    "Feature_045",
    "Feature_046",
    "Feature_047",
    "Feature_048",
    "Feature_049",
    "Feature_050"
  ],
  "generation_timestamp": "2026-01-29T02:29:01.542135",
  "generation_method": "Correlated Binomial pairs with controlled phi coefficient"
}